{
  "Version": "2012-10-17",
  "Statement": [
      {
          "Effect": "Allow",
          "Action": [
              "autoscaling:CompleteLifecycleAction",
              "autoscaling:DeleteLifecycleHook",
              "autoscaling:DescribeAutoScalingGroups",
              "autoscaling:DescribeLifecycleHooks",
              "autoscaling:PutLifecycleHook",
              "autoscaling:RecordLifecycleActionHeartbeat",
              "autoscaling:CreateAutoScalingGroup",
              "autoscaling:UpdateAutoScalingGroup",
              "autoscaling:EnableMetricsCollection",
              "autoscaling:DescribePolicies",
              "autoscaling:DescribeScheduledActions",
              "autoscaling:DescribeNotificationConfigurations",
              "autoscaling:SuspendProcesses",
              "autoscaling:ResumeProcesses",
              "autoscaling:AttachLoadBalancers",
              "autoscaling:AttachLoadBalancerTargetGroups",
              "autoscaling:PutScalingPolicy",
              "autoscaling:PutScheduledUpdateGroupAction",
              "autoscaling:PutNotificationConfiguration",
              "autoscaling:PutWarmPool",
              "autoscaling:DescribeScalingActivities",
              "autoscaling:DeleteAutoScalingGroup",
              "ec2:DescribeInstanceStatus",
              "ec2:TerminateInstances",
              "tag:GetResources",
              "sns:Publish",
              "cloudwatch:DescribeAlarms",
              "cloudwatch:PutMetricAlarm",
              "elasticloadbalancing:DescribeLoadBalancers",
              "elasticloadbalancing:DescribeInstanceHealth",
              "elasticloadbalancing:RegisterInstancesWithLoadBalancer",
              "elasticloadbalancing:DeregisterInstancesFromLoadBalancer",
              "elasticloadbalancing:DescribeTargetGroups",
              "elasticloadbalancing:DescribeTargetHealth",
              "elasticloadbalancing:RegisterTargets",
              "elasticloadbalancing:DeregisterTargets",
              "iam:PassRole",
              "ec2:CreateTags",
              "ec2:RunInstances",
              "ec2:DescribeAddresses",
              "ec2:DescribeCoipPools",
              "ec2:DescribeInstances",
              "ec2:DescribeNetworkInterfaces",
              "ec2:DescribeSubnets",
              "ec2:DescribeSecurityGroups",
              "ec2:DescribeVpcs",
              "ec2:DescribeInternetGateways",
              "ec2:DescribeAccountAttributes",
              "ec2:DescribeClassicLinkInstances",
              "ec2:DescribeVpcClassicLink",
              "ec2:CreateSecurityGroup",
              "ec2:CreateNetworkInterface",
              "ec2:DeleteNetworkInterface",
              "ec2:GetCoipPoolUsage",
              "ec2:ModifyNetworkInterfaceAttribute",
              "ec2:AllocateAddress",
              "ec2:AuthorizeSecurityGroupIngress",
              "ec2:AssociateAddress",
              "ec2:DisassociateAddress",
              "ec2:AttachNetworkInterface",
              "ec2:DetachNetworkInterface",
              "ec2:AssignPrivateIpAddresses",
              "ec2:AssignIpv6Addresses",
              "ec2:ReleaseAddress",
              "ec2:UnassignIpv6Addresses",
              "ec2:DescribeVpcPeeringConnections",
              "logs:CreateLogDelivery",
              "logs:GetLogDelivery",
              "logs:UpdateLogDelivery",
              "logs:DeleteLogDelivery",
              "logs:ListLogDeliveries",
              "outposts:GetOutpostInstanceTypes"
          ],
          "Resource": "*"
      }
  ]
}